README.rst
setup.py
capillary/__init__.py
capillary/tasks.py
capillary/utils.py
capillary.egg-info/PKG-INFO
capillary.egg-info/SOURCES.txt
capillary.egg-info/dependency_links.txt
capillary.egg-info/requires.txt
capillary.egg-info/top_level.txt