Metadata-Version: 1.0
Name: capillary
Version: 0.0.1
Summary: Declarative workflows for celery.
Home-page: https://github.com/celery-capillary/capillary
Author: Domen Kožar, Aaron McMillin
Author-email: aaron@mcmillinclan.org
License: UNKNOWN
Platform: UNKNOWN
